specify_cli/__init__.py
speckitpro-0.0.23.dist-info/METADATA
speckitpro-0.0.23.dist-info/WHEEL
speckitpro-0.0.23.dist-info/entry_points.txt
speckitpro-0.0.23.dist-info/licenses/LICENSE
speckitpro-0.0.23.dist-info/RECORD
