Metadata-Version: 2.4
Name: SpeckitPro
Version: 0.0.23
Summary: SpecifyPro CLI, part of Imam Sanghaar's Speckit Pro. A tool to bootstrap your projects for Spec-Driven Development (SDD).
License-File: LICENSE
Requires-Python: >=3.11
Requires-Dist: httpx[socks]
Requires-Dist: platformdirs
Requires-Dist: readchar
Requires-Dist: rich
Requires-Dist: truststore>=0.10.4
Requires-Dist: typer
